[
        {
         "Sexo": "M",
         "Recinto": "Paraiso",
         "Promedio": 8.17,
         "CA": 15,
         "EC": 15,
         "EA": 19,
         "OR": 12,
         "CA-EC": 0,
         "EA-OR": 7,
         "Estilo": "ACOMODADOR"
        },
        {
         "Sexo": "M",
         "Recinto": "Paraiso",
         "Promedio": 6.33,
         "CA": 16,
         "EC": 17,
         "EA": 18,
         "OR": 19,
         "CA-EC": -1,
         "EA-OR": -1,
         "Estilo": "DIVERGENTE"
        },
        {
         "Sexo": "M",
         "Recinto": "Paraiso",
         "Promedio": 7.07,
         "CA": 15,
         "EC": 13,
         "EA": 17,
         "OR": 17,
         "CA-EC": 2,
         "EA-OR": 0,
         "Estilo": "DIVERGENTE"
        },
        {
         "Sexo": "M",
         "Recinto": "Turrialba",
         "Promedio": 6.6,
         "CA": 19,
         "EC": 13,
         "EA": 13,
         "OR": 20,
         "CA-EC": 6,
         "EA-OR": -7,
         "Estilo": "ASIMILADOR"
        },
        {
         "Sexo": "F",
         "Recinto": "Turrialba",
         "Promedio": 7.77,
         "CA": 19,
         "EC": 11,
         "EA": 14,
         "OR": 17,
         "CA-EC": 8,
         "EA-OR": -3,
         "Estilo": "ASIMILADOR"
        },
        {
         "Sexo": "M",
         "Recinto": "Turrialba",
         "Promedio": 7.87,
         "CA": 18,
         "EC": 12,
         "EA": 21,
         "OR": 14,
         "CA-EC": 6,
         "EA-OR": 7,
         "Estilo": "CONVERGENTE"
        },
        {
         "Sexo": "F",
         "Recinto": "Paraiso",
         "Promedio": 7.53,
         "CA": 11,
         "EC": 19,
         "EA": 16,
         "OR": 16,
         "CA-EC": -8,
         "EA-OR": 0,
         "Estilo": "DIVERGENTE"
        },
        {
         "Sexo": "M",
         "Recinto": "Paraiso",
         "Promedio": 7,
         "CA": 19,
         "EC": 14,
         "EA": 19,
         "OR": 18,
         "CA-EC": 5,
         "EA-OR": 1,
         "Estilo": "ASIMILADOR"
        },
        {
         "Sexo": "M",
         "Recinto": "Paraiso",
         "Promedio": 8,
         "CA": 16,
         "EC": 17,
         "EA": 16,
         "OR": 15,
         "CA-EC": -1,
         "EA-OR": 1,
         "Estilo": "DIVERGENTE"
        },
        {
         "Sexo": "M",
         "Recinto": "Paraiso",
         "Promedio": 7.9,
         "CA": 19,
         "EC": 11,
         "EA": 19,
         "OR": 17,
         "CA-EC": 8,
         "EA-OR": 2,
         "Estilo": "ASIMILADOR"
        },
        {
         "Sexo": "M",
         "Recinto": "Turrialba",
         "Promedio": 7.5,
         "CA": 19,
         "EC": 16,
         "EA": 13,
         "OR": 16,
         "CA-EC": 3,
         "EA-OR": -3,
         "Estilo": "ASIMILADOR"
        },
        {
         "Sexo": "M",
         "Recinto": "Paraiso",
         "Promedio": 7,
         "CA": 13,
         "EC": 14,
         "EA": 21,
         "OR": 13,
         "CA-EC": -1,
         "EA-OR": 8,
         "Estilo": "ACOMODADOR"
        },
        {
         "Sexo": "F",
         "Recinto": "Paraiso",
         "Promedio": 7.4,
         "CA": 21,
         "EC": 14,
         "EA": 12,
         "OR": 18,
         "CA-EC": 7,
         "EA-OR": -6,
         "Estilo": "ASIMILADOR"
        },
        {
         "Sexo": "M",
         "Recinto": "Paraiso",
         "Promedio": 7.41,
         "CA": 16,
         "EC": 15,
         "EA": 18,
         "OR": 19,
         "CA-EC": 1,
         "EA-OR": -1,
         "Estilo": "DIVERGENTE"
        },
        {
         "Sexo": "F",
         "Recinto": "Paraiso",
         "Promedio": 7.2,
         "CA": 18,
         "EC": 10,
         "EA": 22,
         "OR": 13,
         "CA-EC": 8,
         "EA-OR": 9,
         "Estilo": "CONVERGENTE"
        },
        {
         "Sexo": "M",
         "Recinto": "Turrialba",
         "Promedio": 8.5,
         "CA": 17,
         "EC": 15,
         "EA": 13,
         "OR": 18,
         "CA-EC": 2,
         "EA-OR": -5,
         "Estilo": "DIVERGENTE"
        },
        {
         "Sexo": "F",
         "Recinto": "Paraiso",
         "Promedio": 7.82,
         "CA": 15,
         "EC": 17,
         "EA": 19,
         "OR": 15,
         "CA-EC": -2,
         "EA-OR": 4,
         "Estilo": "ACOMODADOR"
        },
        {
         "Sexo": "M",
         "Recinto": "Turrialba",
         "Promedio": 7.54,
         "CA": 20,
         "EC": 15,
         "EA": 15,
         "OR": 12,
         "CA-EC": 5,
         "EA-OR": 3,
         "Estilo": "CONVERGENTE"
        },
        {
         "Sexo": "M",
         "Recinto": "Turrialba",
         "Promedio": 8.41,
         "CA": 17,
         "EC": 15,
         "EA": 15,
         "OR": 17,
         "CA-EC": 2,
         "EA-OR": -2,
         "Estilo": "DIVERGENTE"
        },
        {
         "Sexo": "M",
         "Recinto": "Turrialba",
         "Promedio": 8.11,
         "CA": 12,
         "EC": 17,
         "EA": 12,
         "OR": 21,
         "CA-EC": -5,
         "EA-OR": -9,
         "Estilo": "DIVERGENTE"
        },
        {
         "Sexo": "F",
         "Recinto": "Paraiso",
         "Promedio": 7.25,
         "CA": 21,
         "EC": 10,
         "EA": 11,
         "OR": 23,
         "CA-EC": 11,
         "EA-OR": -12,
         "Estilo": "ASIMILADOR"
        },
        {
         "Sexo": "M",
         "Recinto": "Paraiso",
         "Promedio": 8.06,
         "CA": 17,
         "EC": 13,
         "EA": 19,
         "OR": 14,
         "CA-EC": 4,
         "EA-OR": 5,
         "Estilo": "CONVERGENTE"
        },
        {
         "Sexo": "M",
         "Recinto": "Turrialba",
         "Promedio": 7.75,
         "CA": 11,
         "EC": 15,
         "EA": 20,
         "OR": 16,
         "CA-EC": -4,
         "EA-OR": 4,
         "Estilo": "ACOMODADOR"
        },
        {
         "Sexo": "M",
         "Recinto": "Turrialba",
         "Promedio": 7.09,
         "CA": 13,
         "EC": 15,
         "EA": 22,
         "OR": 13,
         "CA-EC": -2,
         "EA-OR": 9,
         "Estilo": "ACOMODADOR"
        },
        {
         "Sexo": "M",
         "Recinto": "Paraiso",
         "Promedio": 6.14,
         "CA": 17,
         "EC": 13,
         "EA": 16,
         "OR": 15,
         "CA-EC": 4,
         "EA-OR": 1,
         "Estilo": "ASIMILADOR"
        },
        {
         "Sexo": "M",
         "Recinto": "Paraiso",
         "Promedio": 7.72,
         "CA": 17,
         "EC": 13,
         "EA": 21,
         "OR": 14,
         "CA-EC": 4,
         "EA-OR": 7,
         "Estilo": "CONVERGENTE"
        },
        {
         "Sexo": "M",
         "Recinto": "Paraiso",
         "Promedio": 7.68,
         "CA": 15,
         "EC": 16,
         "EA": 13,
         "OR": 17,
         "CA-EC": -1,
         "EA-OR": -4,
         "Estilo": "DIVERGENTE"
        },
        {
         "Sexo": "F",
         "Recinto": "Paraiso",
         "Promedio": 7.5,
         "CA": 16,
         "EC": 11,
         "EA": 20,
         "OR": 12,
         "CA-EC": 5,
         "EA-OR": 8,
         "Estilo": "CONVERGENTE"
        },
        {
         "Sexo": "M",
         "Recinto": "Turrialba",
         "Promedio": 7.9399999999999995,
         "CA": 14,
         "EC": 15,
         "EA": 15,
         "OR": 17,
         "CA-EC": -1,
         "EA-OR": -2,
         "Estilo": "DIVERGENTE"
        },
        {
         "Sexo": "M",
         "Recinto": "Paraiso",
         "Promedio": 7.86,
         "CA": 18,
         "EC": 11,
         "EA": 21,
         "OR": 18,
         "CA-EC": 7,
         "EA-OR": 3,
         "Estilo": "CONVERGENTE"
        },
        {
         "Sexo": "M",
         "Recinto": "Turrialba",
         "Promedio": 6.62,
         "CA": 14,
         "EC": 11,
         "EA": 18,
         "OR": 15,
         "CA-EC": 3,
         "EA-OR": 3,
         "Estilo": "CONVERGENTE"
        },
        {
         "Sexo": "M",
         "Recinto": "Turrialba",
         "Promedio": 8.13,
         "CA": 16,
         "EC": 17,
         "EA": 14,
         "OR": 21,
         "CA-EC": -1,
         "EA-OR": -7,
         "Estilo": "DIVERGENTE"
        },
        {
         "Sexo": "F",
         "Recinto": "Turrialba",
         "Promedio": 6.88,
         "CA": 17,
         "EC": 13,
         "EA": 22,
         "OR": 11,
         "CA-EC": 4,
         "EA-OR": 11,
         "Estilo": "CONVERGENTE"
        },
        {
         "Sexo": "F",
         "Recinto": "Paraiso",
         "Promedio": 8.5,
         "CA": 16,
         "EC": 15,
         "EA": 18,
         "OR": 15,
         "CA-EC": 1,
         "EA-OR": 3,
         "Estilo": "ACOMODADOR"
        },
        {
         "Sexo": "F",
         "Recinto": "Paraiso",
         "Promedio": 7,
         "CA": 19,
         "EC": 18,
         "EA": 20,
         "OR": 11,
         "CA-EC": 1,
         "EA-OR": 9,
         "Estilo": "ACOMODADOR"
        },
        {
         "Sexo": "M",
         "Recinto": "Turrialba",
         "Promedio": 7.83,
         "CA": 12,
         "EC": 15,
         "EA": 16,
         "OR": 18,
         "CA-EC": -3,
         "EA-OR": -2,
         "Estilo": "DIVERGENTE"
        },
        {
         "Sexo": "M",
         "Recinto": "Turrialba",
         "Promedio": 7.13,
         "CA": 9,
         "EC": 21,
         "EA": 18,
         "OR": 17,
         "CA-EC": -12,
         "EA-OR": 1,
         "Estilo": "DIVERGENTE"
        },
        {
         "Sexo": "M",
         "Recinto": "Paraiso",
         "Promedio": 7.63,
         "CA": 18,
         "EC": 11,
         "EA": 17,
         "OR": 14,
         "CA-EC": 7,
         "EA-OR": 3,
         "Estilo": "CONVERGENTE"
        },
        {
         "Sexo": "M",
         "Recinto": "Paraiso",
         "Promedio": 8.06,
         "CA": 10,
         "EC": 17,
         "EA": 17,
         "OR": 17,
         "CA-EC": -7,
         "EA-OR": 0,
         "Estilo": "DIVERGENTE"
        },
        {
         "Sexo": "M",
         "Recinto": "Paraiso",
         "Promedio": 7.72,
         "CA": 16,
         "EC": 14,
         "EA": 19,
         "OR": 14,
         "CA-EC": 2,
         "EA-OR": 5,
         "Estilo": "ACOMODADOR"
        },
        {
         "Sexo": "M",
         "Recinto": "Turrialba",
         "Promedio": 8.63,
         "CA": 19,
         "EC": 12,
         "EA": 18,
         "OR": 15,
         "CA-EC": 7,
         "EA-OR": 3,
         "Estilo": "CONVERGENTE"
        },
        {
         "Sexo": "F",
         "Recinto": "Paraiso",
         "Promedio": 7.32,
         "CA": 17,
         "EC": 13,
         "EA": 20,
         "OR": 13,
         "CA-EC": 4,
         "EA-OR": 7,
         "Estilo": "CONVERGENTE"
        },
        {
         "Sexo": "M",
         "Recinto": "Turrialba",
         "Promedio": 7.25,
         "CA": 17,
         "EC": 14,
         "EA": 16,
         "OR": 18,
         "CA-EC": 3,
         "EA-OR": -2,
         "Estilo": "ASIMILADOR"
        },
        {
         "Sexo": "M",
         "Recinto": "Turrialba",
         "Promedio": 7.72,
         "CA": 20,
         "EC": 13,
         "EA": 11,
         "OR": 19,
         "CA-EC": 7,
         "EA-OR": -8,
         "Estilo": "ASIMILADOR"
        },
        {
         "Sexo": "M",
         "Recinto": "Paraiso",
         "Promedio": 7.39,
         "CA": 10,
         "EC": 15,
         "EA": 16,
         "OR": 19,
         "CA-EC": -5,
         "EA-OR": -3,
         "Estilo": "DIVERGENTE"
        },
        {
         "Sexo": "M",
         "Recinto": "Paraiso",
         "Promedio": 7.78,
         "CA": 20,
         "EC": 12,
         "EA": 18,
         "OR": 12,
         "CA-EC": 8,
         "EA-OR": 6,
         "Estilo": "CONVERGENTE"
        },
        {
         "Sexo": "M",
         "Recinto": "Paraiso",
         "Promedio": 7.62,
         "CA": 19,
         "EC": 17,
         "EA": 15,
         "OR": 18,
         "CA-EC": 2,
         "EA-OR": -3,
         "Estilo": "DIVERGENTE"
        },
        {
         "Sexo": "M",
         "Recinto": "Turrialba",
         "Promedio": 8,
         "CA": 16,
         "EC": 12,
         "EA": 14,
         "OR": 19,
         "CA-EC": 4,
         "EA-OR": -5,
         "Estilo": "ASIMILADOR"
        },
        {
         "Sexo": "M",
         "Recinto": "Turrialba",
         "Promedio": 8.83,
         "CA": 17,
         "EC": 13,
         "EA": 16,
         "OR": 15,
         "CA-EC": 4,
         "EA-OR": 1,
         "Estilo": "ASIMILADOR"
        },
        {
         "Sexo": "M",
         "Recinto": "Paraiso",
         "Promedio": 8.5,
         "CA": 15,
         "EC": 12,
         "EA": 14,
         "OR": 23,
         "CA-EC": 3,
         "EA-OR": -9,
         "Estilo": "ASIMILADOR"
        },
        {
         "Sexo": "M",
         "Recinto": "Turrialba",
         "Promedio": 8,
         "CA": 11,
         "EC": 16,
         "EA": 17,
         "OR": 19,
         "CA-EC": -5,
         "EA-OR": -2,
         "Estilo": "DIVERGENTE"
        },
        {
         "Sexo": "M",
         "Recinto": "Turrialba",
         "Promedio": 8.06,
         "CA": 17,
         "EC": 12,
         "EA": 21,
         "OR": 15,
         "CA-EC": 5,
         "EA-OR": 6,
         "Estilo": "CONVERGENTE"
        },
        {
         "Sexo": "M",
         "Recinto": "Turrialba",
         "Promedio": 7.14,
         "CA": 19,
         "EC": 14,
         "EA": 21,
         "OR": 9,
         "CA-EC": 5,
         "EA-OR": 12,
         "Estilo": "CONVERGENTE"
        },
        {
         "Sexo": "M",
         "Recinto": "Turrialba",
         "Promedio": 7.44,
         "CA": 15,
         "EC": 14,
         "EA": 17,
         "OR": 15,
         "CA-EC": 1,
         "EA-OR": 2,
         "Estilo": "DIVERGENTE"
        },
        {
         "Sexo": "M",
         "Recinto": "Turrialba",
         "Promedio": 8,
         "CA": 20,
         "EC": 10,
         "EA": 18,
         "OR": 12,
         "CA-EC": 10,
         "EA-OR": 6,
         "Estilo": "CONVERGENTE"
        },
        {
         "Sexo": "M",
         "Recinto": "Turrialba",
         "Promedio": 7.75,
         "CA": 14,
         "EC": 18,
         "EA": 13,
         "OR": 14,
         "CA-EC": -4,
         "EA-OR": -1,
         "Estilo": "DIVERGENTE"
        },
        {
         "Sexo": "M",
         "Recinto": "Paraiso",
         "Promedio": 7.34,
         "CA": 15,
         "EC": 16,
         "EA": 12,
         "OR": 20,
         "CA-EC": -1,
         "EA-OR": -8,
         "Estilo": "DIVERGENTE"
        },
        {
         "Sexo": "M",
         "Recinto": "Paraiso",
         "Promedio": 7.33,
         "CA": 18,
         "EC": 14,
         "EA": 13,
         "OR": 17,
         "CA-EC": 4,
         "EA-OR": -4,
         "Estilo": "ASIMILADOR"
        },
        {
         "Sexo": "M",
         "Recinto": "Turrialba",
         "Promedio": 7.56,
         "CA": 18,
         "EC": 14,
         "EA": 17,
         "OR": 18,
         "CA-EC": 4,
         "EA-OR": -1,
         "Estilo": "ASIMILADOR"
        },
        {
         "Sexo": "M",
         "Recinto": "Turrialba",
         "Promedio": 7.84,
         "CA": 17,
         "EC": 14,
         "EA": 12,
         "OR": 18,
         "CA-EC": 3,
         "EA-OR": -6,
         "Estilo": "ASIMILADOR"
        },
        {
         "Sexo": "M",
         "Recinto": "Paraiso",
         "Promedio": 8.29,
         "CA": 19,
         "EC": 8,
         "EA": 12,
         "OR": 21,
         "CA-EC": 11,
         "EA-OR": -9,
         "Estilo": "ASIMILADOR"
        },
        {
         "Sexo": "M",
         "Recinto": "Paraiso",
         "Promedio": 8.79,
         "CA": 20,
         "EC": 15,
         "EA": 15,
         "OR": 15,
         "CA-EC": 5,
         "EA-OR": 0,
         "Estilo": "ASIMILADOR"
        },
        {
         "Sexo": "M",
         "Recinto": "Paraiso",
         "Promedio": 7.5,
         "CA": 7,
         "EC": 19,
         "EA": 19,
         "OR": 15,
         "CA-EC": -12,
         "EA-OR": 4,
         "Estilo": "ACOMODADOR"
        },
        {
         "Sexo": "M",
         "Recinto": "Turrialba",
         "Promedio": 8.39,
         "CA": 19,
         "EC": 11,
         "EA": 21,
         "OR": 12,
         "CA-EC": 8,
         "EA-OR": 9,
         "Estilo": "CONVERGENTE"
        },
        {
         "Sexo": "M",
         "Recinto": "Paraiso",
         "Promedio": 7.43,
         "CA": 21,
         "EC": 10,
         "EA": 20,
         "OR": 10,
         "CA-EC": 11,
         "EA-OR": 10,
         "Estilo": "CONVERGENTE"
        },
        {
         "Sexo": "M",
         "Recinto": "Paraiso",
         "Promedio": 8.43,
         "CA": 14,
         "EC": 9,
         "EA": 24,
         "OR": 14,
         "CA-EC": 5,
         "EA-OR": 10,
         "Estilo": "CONVERGENTE"
        },
        {
         "Sexo": "M",
         "Recinto": "Turrialba",
         "Promedio": 7.8,
         "CA": 17,
         "EC": 14,
         "EA": 18,
         "OR": 14,
         "CA-EC": 3,
         "EA-OR": 4,
         "Estilo": "CONVERGENTE"
        },
        {
         "Sexo": "M",
         "Recinto": "Turrialba",
         "Promedio": 7.2,
         "CA": 12,
         "EC": 15,
         "EA": 18,
         "OR": 14,
         "CA-EC": -3,
         "EA-OR": 4,
         "Estilo": "ACOMODADOR"
        },
        {
         "Sexo": "M",
         "Recinto": "Turrialba",
         "Promedio": 7.3,
         "CA": 17,
         "EC": 13,
         "EA": 17,
         "OR": 16,
         "CA-EC": 4,
         "EA-OR": 1,
         "Estilo": "ASIMILADOR"
        },
        {
         "Sexo": "F",
         "Recinto": "Paraiso",
         "Promedio": 9,
         "CA": 17,
         "EC": 11,
         "EA": 18,
         "OR": 18,
         "CA-EC": 6,
         "EA-OR": 0,
         "Estilo": "ASIMILADOR"
        },
        {
         "Sexo": "M",
         "Recinto": "Turrialba",
         "Promedio": 6.57,
         "CA": 14,
         "EC": 14,
         "EA": 20,
         "OR": 13,
         "CA-EC": 0,
         "EA-OR": 7,
         "Estilo": "ACOMODADOR"
        },
        {
         "Sexo": "F",
         "Recinto": "Turrialba",
         "Promedio": 7.63,
         "CA": 14,
         "EC": 16,
         "EA": 20,
         "OR": 13,
         "CA-EC": -2,
         "EA-OR": 7,
         "Estilo": "ACOMODADOR"
        },
        {
         "Sexo": "M",
         "Recinto": "Turrialba",
         "Promedio": 8.83,
         "CA": 17,
         "EC": 13,
         "EA": 20,
         "OR": 16,
         "CA-EC": 4,
         "EA-OR": 4,
         "Estilo": "CONVERGENTE"
        },
        {
         "Sexo": "M",
         "Recinto": "Turrialba",
         "Promedio": 7.6899999999999995,
         "CA": 13,
         "EC": 14,
         "EA": 16,
         "OR": 15,
         "CA-EC": -1,
         "EA-OR": 1,
         "Estilo": "DIVERGENTE"
        },
        {
         "Sexo": "M",
         "Recinto": "Paraiso",
         "Promedio": 7,
         "CA": 18,
         "EC": 12,
         "EA": 17,
         "OR": 16,
         "CA-EC": 6,
         "EA-OR": 1,
         "Estilo": "ASIMILADOR"
        },
        {
         "Sexo": "M",
         "Recinto": "Turrialba",
         "Promedio": 8.23,
         "CA": 14,
         "EC": 16,
         "EA": 19,
         "OR": 15,
         "CA-EC": -2,
         "EA-OR": 4,
         "Estilo": "ACOMODADOR"
        },
        {
         "Sexo": "M",
         "Recinto": "Turrialba",
         "Promedio": 8.64,
         "CA": 11,
         "EC": 15,
         "EA": 18,
         "OR": 14,
         "CA-EC": -4,
         "EA-OR": 4,
         "Estilo": "ACOMODADOR"
        }
       ]

